fishbowl_inventory/__init__.py
fishbowl_inventory/firebase.py
fishbowl_inventory/shipment.py
fishbowl_inventory-0.0.3.dist-info/METADATA
fishbowl_inventory-0.0.3.dist-info/WHEEL
fishbowl_inventory-0.0.3.dist-info/licenses/LICENSE
fishbowl_inventory-0.0.3.dist-info/RECORD
