Metadata-Version: 2.4
Name: fishbowl_inventory
Version: 0.0.3
Summary: A helpful package for working with Fishbowl inventory reports in python.
Project-URL: Homepage, https://github.com/jsynstelien/fishbowl-inventory
Project-URL: Issues, https://github.com/jsynstelien/fishbowl-inventory/issues
Author-email: Justin Synstelien <justin.synstelien3@gmail.com>
License-File: LICENSE
Classifier: License :: OSI Approved :: MIT License
Classifier: Operating System :: OS Independent
Classifier: Programming Language :: Python :: 3
Requires-Python: >=3.8
Requires-Dist: firebase-admin
